mediawiki_mcp_server/main.py
mediawiki_mcp_server-0.0.1.dist-info/METADATA
mediawiki_mcp_server-0.0.1.dist-info/WHEEL
mediawiki_mcp_server-0.0.1.dist-info/entry_points.txt
mediawiki_mcp_server-0.0.1.dist-info/RECORD
