Metadata-Version: 2.4
Name: mediawiki-mcp-server
Version: 0.0.1
Summary: A MCP server for MediaWiki
Requires-Python: >=3.13
Requires-Dist: httpx<0.28
Requires-Dist: loguru>=0.7.3
Requires-Dist: mcp[cli]>=1.6.0
